nvidia_tensorrt/__init__.py
nvidia_tensorrt-99.0.0.dist-info/LICENSE.txt
nvidia_tensorrt-99.0.0.dist-info/METADATA
nvidia_tensorrt-99.0.0.dist-info/WHEEL
nvidia_tensorrt-99.0.0.dist-info/top_level.txt
nvidia_tensorrt-99.0.0.dist-info/zip-safe
nvidia_tensorrt-99.0.0.dist-info/RECORD
