Metadata-Version: 2.1
Name: nvidia-tensorrt
Version: 99.0.0
Summary: A high performance deep learning inference library
Home-page: https://developer.nvidia.com/tensorrt
Author: NVIDIA Corporation
License: Proprietary
Download-URL: https://github.com/nvidia/tensorrt/tags
Keywords: nvidia tensorrt deeplearning inference
Platform: manylinux_2_17_x86_64
Classifier: License :: Other/Proprietary License
Classifier: Intended Audience :: Developers
Classifier: Programming Language :: Python :: 3
License-File: LICENSE.txt
Requires-Dist: tensorrt
